{
    "theme_cat":[
        {"post_1":[{
            "title":"우리집 고양이 보고 가",
            "date":"2023.06.24 20:01",
            "uploader":"배곧동낭만사나이김준성",
            "context":"귀엽지?",
            "images":[{"image_1":"1"}],
            "views":"182",
            "likes":"3",
            "share":"0",

            "comments":[
                {"comment_1":[{
                    "comment":"귀엽네",
                    "date":"2023.06.24 20:03",
                    "uploader":"배곧동낭만교사박종갑"
                }]}
            ]

        }]},
        {"post_2":[{}]},
        {"post_3":[{}]}
        ]
    }